odoo/addons/product_variant_configurator_manual_creation/README.rst
odoo/addons/product_variant_configurator_manual_creation/__init__.py
odoo/addons/product_variant_configurator_manual_creation/__manifest__.py
odoo/addons/product_variant_configurator_manual_creation/i18n/it.po
odoo/addons/product_variant_configurator_manual_creation/i18n/product_variant_configurator_manual_creation.pot
odoo/addons/product_variant_configurator_manual_creation/models/__init__.py
odoo/addons/product_variant_configurator_manual_creation/models/product_template.py
odoo/addons/product_variant_configurator_manual_creation/readme/CONTRIBUTORS.rst
odoo/addons/product_variant_configurator_manual_creation/readme/DESCRIPTION.rst
odoo/addons/product_variant_configurator_manual_creation/security/ir.model.access.csv
odoo/addons/product_variant_configurator_manual_creation/static/description/icon.png
odoo/addons/product_variant_configurator_manual_creation/static/description/index.html
odoo/addons/product_variant_configurator_manual_creation/tests/__init__.py
odoo/addons/product_variant_configurator_manual_creation/tests/test_product_variant_configurator_manual_creation.py
odoo/addons/product_variant_configurator_manual_creation/views/product_template_view.xml
odoo/addons/product_variant_configurator_manual_creation/wizards/__init__.py
odoo/addons/product_variant_configurator_manual_creation/wizards/wizard_product_variant_configurator_manual_creation.py
odoo/addons/product_variant_configurator_manual_creation/wizards/wizard_product_variant_configurator_manual_creation_view.xml
odoo13_addon_product_variant_configurator_manual_creation-13.0.1.0.1.dev10.dist-info/METADATA
odoo13_addon_product_variant_configurator_manual_creation-13.0.1.0.1.dev10.dist-info/WHEEL
odoo13_addon_product_variant_configurator_manual_creation-13.0.1.0.1.dev10.dist-info/top_level.txt
odoo13_addon_product_variant_configurator_manual_creation-13.0.1.0.1.dev10.dist-info/RECORD
